lvsm_pytorch/__init__.py
lvsm_pytorch/lvsm.py
lvsm_pytorch/tensor_typing.py
lvsm_pytorch-0.1.6.dist-info/METADATA
lvsm_pytorch-0.1.6.dist-info/WHEEL
lvsm_pytorch-0.1.6.dist-info/licenses/LICENSE
lvsm_pytorch-0.1.6.dist-info/RECORD
