Metadata-Version: 2.4
Name: lvsm-pytorch
Version: 0.1.6
Summary: LVSM - Pytorch
Project-URL: Homepage, https://pypi.org/project/lvsm-pytorch/
Project-URL: Repository, https://github.com/lucidrains/lvsm-pytorch
Author-email: Phil Wang <lucidrains@gmail.com>
License: MIT License
License-File: LICENSE
Keywords: artificial intelligence,attention mechanism,deep learning,novel view synthesis,transformers
Classifier: Development Status :: 4 - Beta
Classifier: Intended Audience :: Developers
Classifier: License :: OSI Approved :: MIT License
Classifier: Programming Language :: Python :: 3.9
Classifier: Topic :: Scientific/Engineering :: Artificial Intelligence
Requires-Python: >=3.9
Requires-Dist: einops>=0.8.0
Requires-Dist: einx>=0.3.0
Requires-Dist: jaxtyping
Requires-Dist: torch>=2.0
Requires-Dist: torchvision
Requires-Dist: x-transformers>=1.42.5
Provides-Extra: examples
Provides-Extra: test
Requires-Dist: pytest; extra == 'test'
